ipywidgets_game_maze/Ant.py
ipywidgets_game_maze/Maze.py
ipywidgets_game_maze/MazePlayer.py
ipywidgets_game_maze/Object3D.py
ipywidgets_game_maze/StaticObject.py
ipywidgets_game_maze/Visualisation.py
ipywidgets_game_maze/__init__.py
ipywidgets_game_maze/timer.py
ipywidgets_game_maze/value_player_widget.py
ipywidgets_game_maze/__global__/__init__.py
ipywidgets_game_maze/__global__/en.py
ipywidgets_game_maze/__global__/fr.py
ipywidgets_game_maze/images/blanc.jpg
ipywidgets_game_maze/images/gagne.jpg
ipywidgets_game_maze/images/perdu.png
ipywidgets_game_maze/images/seville.jpg
ipywidgets_game_maze/images/tete3.jpg
ipywidgets_game_maze/images/win.jpg
ipywidgets_game_maze/lab/lab.json
ipywidgets_game_maze/lab/laby3d.json
ipywidgets_game_maze/static/seville.jpg
ipywidgets_game_maze/static/tete3.jpg
ipywidgets_game_maze-0.2.0.data/data/share/jupyter/nbextensions/ipywidgets_game_maze/seville.jpg
ipywidgets_game_maze-0.2.0.data/data/share/jupyter/nbextensions/ipywidgets_game_maze/tete3.jpg
ipywidgets_game_maze-0.2.0.dist-info/LICENSE
ipywidgets_game_maze-0.2.0.dist-info/METADATA
ipywidgets_game_maze-0.2.0.dist-info/WHEEL
ipywidgets_game_maze-0.2.0.dist-info/top_level.txt
ipywidgets_game_maze-0.2.0.dist-info/RECORD
